streamlit_wavesurfer/__init__.py
streamlit_wavesurfer/py.typed
streamlit_wavesurfer/utils.py
streamlit_wavesurfer/frontend/dist/index.html
streamlit_wavesurfer/frontend/dist/assets/index-CcJ8-_3L.js
streamlit_wavesurfer/frontend/dist/assets/index-DZOvgDGO.css
streamlit_wavesurfer/frontend/node_modules/flatted/python/flatted.py
streamlit_wavesurfer-0.2.1.dist-info/METADATA
streamlit_wavesurfer-0.2.1.dist-info/WHEEL
streamlit_wavesurfer-0.2.1.dist-info/top_level.txt
streamlit_wavesurfer-0.2.1.dist-info/RECORD
